{"tileset":1,"movingBlocks":[],"shapes":[[1,3,2,3],[0,7,2,7],[5,7,11,7],[9,10,11,10],[1,11,6,11],[0,15,1,15],[2,17,3,17],[4,19,5,19],[11,19,13,19],[10,14,13,14],[19,3,22,3],[18,11,25,11],[20,16,22,16],[18,19,25,19],[26,19,27,19],[28,19,29,19],[30,19,31,19],[25,15,31,15],[28,3,31,3],[36,13,40,13],[36,19,40,19],[36,5,38,5]],"ladders":[[0,2,2],[11,6,5],[13,13,4],[17,10,6],[25,10,4],[31,2,10]],"effect":"none","portals":[{"pos":[21,9],"dest":[3,0,1]},{"pos":[20,1],"dest":[3,0,2]},{"pos":[38,17],"terminal":[38,11],"dest":[4,0,0],"wall":[36,13,5]}],"width":40,"hearts":[{"pos":[30,17],"fake":false,"secret":"box"},{"pos":[22,17],"fake":false,"secret":"box"},{"pos":[20,17],"fake":false,"secret":"box"},{"pos":[11,17],"fake":false,"secret":"box"},{"pos":[12,17],"fake":false,"secret":"box"},{"pos":[0,13],"fake":false,"secret":"box"},{"pos":[1,5],"fake":false,"secret":"box"},{"pos":[36,3],"fake":false,"secret":"box"},{"pos":[9,8],"fake":false,"secret":"box"},{"pos":[21,17],"fake":true,"secret":"box"},{"pos":[0,5],"fake":true,"secret":"box"},{"pos":[37,3],"fake":true,"secret":"box"},{"pos":[28,17],"fake":false,"secret":"snowheap"},{"pos":[28,13],"fake":false,"secret":"snowheap"},{"pos":[30,13],"fake":false,"secret":"snowheap"},{"pos":[37,11],"fake":false,"secret":"snowheap"},{"pos":[2,15],"fake":true,"secret":"snowheap"},{"pos":[8,5],"fake":true,"secret":"snowheap"},{"pos":[6,5],"fake":true,"secret":"snowheap"},{"pos":[9,5],"fake":false,"secret":"snowheap"},{"pos":[4,17],"fake":false,"secret":"snowheap"},{"pos":[18,9],"fake":false,"secret":"snowheap"},{"pos":[23,9],"fake":true,"secret":"snowheap"},{"pos":[1,1],"fake":false,"secret":"snowheap"},{"pos":[11,12],"fake":false,"secret":"snowheap"}],"movingPlatforms":[{"path":[[17,3],[13,3],[13,7],[13,3]],"width":1,"speed":0.2},{"path":[[23,3],[26,3]],"width":1,"speed":0.2},{"path":[[33,3],[34,3]],"width":1,"speed":0.2},{"path":[[6,19],[9,19]],"width":1,"speed":0.2},{"path":[[33,13],[34,13]],"width":1,"speed":0.2}],"enemies":[{"path":[[28,4],[32,4]],"rect":[1.0,1.0,0.0,0.0],"weapon":false,"canDie":false,"type":"snowflake","speed":0.2},{"path":[[34,7],[30,7]],"rect":[1.0,1.0,0.0,0.0],"weapon":false,"canDie":false,"type":"snowflake","speed":0.2},{"path":[[27,10],[27,13]],"rect":[1.0,1.0,0.0,0.0],"weapon":false,"canDie":false,"type":"snowflake","speed":0.2},{"path":[[29,13],[29,10]],"rect":[1.0,1.0,0.0,0.0],"weapon":false,"canDie":false,"type":"snowflake","speed":0.3},{"path":[[1,12],[1,16]],"rect":[1.0,1.0,0.0,0.0],"weapon":false,"canDie":false,"type":"snowflake","speed":0.3},{"path":[[3,18],[3,14]],"rect":[1.0,1.0,0.0,0.0],"weapon":false,"canDie":false,"type":"snowflake","speed":0.2},{"path":[[11,0],[11,4],[15,4],[15,0]],"rect":[1.0,1.0,0.0,0.0],"weapon":false,"canDie":false,"type":"snowflake","speed":0.2},{"path":[[29,1]],"rect":[1.0,0.5,0.0,0.5],"weapon":false,"canDie":false,"type":"none","direction":1},{"path":[[10,8]],"rect":[1.0,0.5,0.0,0.5],"weapon":false,"canDie":false,"type":"none","direction":1},{"path":[[5,9]],"rect":[1.0,0.5,0.0,0.5],"weapon":false,"canDie":false,"type":"none","direction":1},{"path":[[1,9]],"rect":[1.0,0.5,0.0,0.5],"weapon":false,"canDie":false,"type":"none","direction":1},{"path":[[39,7]],"rect":[0.5,5.0,0.5,0.0],"weapon":false,"canDie":false,"type":"none","direction":1},{"path":[[2,9],[4,9]],"rect":[0.6,1.0,0.0,0.0],"weapon":true,"shootDelay":1500,"canDie":true,"type":"snowman","speed":0.2},{"path":[[10,12],[12,12]],"rect":[0.6,1.0,0.0,0.0],"weapon":true,"shootDelay":1800,"canDie":true,"type":"snowman","speed":0.2},{"path":[[20,14],[21,14]],"rect":[0.6,1.0,0.0,0.0],"weapon":true,"shootDelay":1300,"canDie":true,"type":"snowman","speed":0.2}],"height":20}